ipfromwebpage/__init__.py
ipfromwebpage/ipfromwebpage.py
ipfromwebpage-1.2.0.dist-info/AUTHORS.md
ipfromwebpage-1.2.0.dist-info/LICENSE.md
ipfromwebpage-1.2.0.dist-info/METADATA
ipfromwebpage-1.2.0.dist-info/WHEEL
ipfromwebpage-1.2.0.dist-info/entry_points.txt
ipfromwebpage-1.2.0.dist-info/RECORD
