Metadata-Version: 2.1
Name: ipfromwebpage
Version: 1.2.0
Summary: Takes a webpage and outputs all ip addresses it finds
Home-page: https://github.com/shepherdjay/ip-from-webpage
License: MIT
Keywords: ipfromwebpage
Author: Jay Shepherd
Author-email: shepherdjay@users.noreply.github.com
Requires-Python: >=3.9
Classifier: Development Status :: 5 - Production/Stable
Classifier: Environment :: Console
Classifier: License :: OSI Approved :: MIT License
Classifier: Programming Language :: Python
Classifier: Programming Language :: Python :: 3
Classifier: Programming Language :: Python :: 3.9
Classifier: Programming Language :: Python :: 3.10
Classifier: Programming Language :: Python :: 3.11
Classifier: Programming Language :: Python :: 3.12
Requires-Dist: beautifulsoup4 (>=4.4,<5.0)
Requires-Dist: netaddr (>=0.8.0,<0.9.0)
Project-URL: Repository, https://github.com/shepherdjay/ip-from-webpage
